{
  "l1_community_health": {
    "title": "社区生态健康"
  },
  "l1_contributor_overview": {
    "title": "贡献总览"
  },
  "l1_developer_ecology": {
    "title": "开发者旅程"
  },
  "l1_supply_chain_security": {
    "title": "开源软件供应链安全"
  },
  "dimensionality_001": {
    "title": "协作效率"
  },
  "dimensionality_002": {
    "title": "社区活力"
  },
  "dimensionality_003": {
    "title": "生态影响力"
  },
  "dimensionality_004": {
    "title": "开放治理"
  },
  "dimensionality_005": {
    "title": "贡献总览"
  },
  "dimensionality_006": {
    "title": "开发者吸引"
  },
  "dimensionality_007": {
    "title": "开发者成长"
  },
  "dimensionality_008": {
    "title": "开发者留存"
  },
  "dimensionality_009": {
    "title": "源码管理"
  },
  "dimensionality_010": {
    "title": "开发与构建"
  },
  "dimensionality_011": {
    "title": "发布与维护"
  },
  "model_001": {
    "title": "响应及时性",
    "desc": "响应及时性模型说明",
    "metrics": {
      "metric_001": {
        "title": "Issue 超过一个周期未响应的占比",
        "desc": "当前周期新建 Issue 超过一个周期未响应的占比，不包括机器人、创建者评论"
      },
      "metric_002": {
        "title": "Issue 首次响应时间",
        "desc": "新建 Issue 周期内首次响应时间，不包括机器人、创建者的评论"
      },
      "metric_003": {
        "title": "Issue 处理时长",
        "desc": "Issue 处理时长均值（天），包含已经关闭的 Issue 以及未解决的 Issue"
      },
      "metric_004": {
        "title": "PR 超过一个周期未响应的占比",
        "desc": "当前周期新建 PR 超过一个周期未响应的占比"
      },
      "metric_005": {
        "title": "PR 首次响应时间",
        "desc": "新建 PR 周期内首次响应的时间，不包括机器人、创建者评论"
      },
      "metric_006": {
        "title": "PR 处理时长",
        "desc": "PR 从创建到合并或关闭的时长均值"
      }
    }
  },
  "model_002": {
    "title": "协作开发质量",
    "desc": "协作开发质量模型说明",
    "metrics": {
      "metric_007": {
        "title": "通过 PR 提交代码的比率",
        "desc": "周期内通过 PR 提交的代码占比"
      },
      "metric_008": {
        "title": "PR 关联 Issue 的比率",
        "desc": "周期内 PR 关联 Issue 的占比"
      },
      "metric_009": {
        "title": "Review 协作比率",
        "desc": "周期内至少有一条非作者 Review 评论或 Approval 记录的 PR 占比"
      },
      "metric_010": {
        "title": "Merge 协作比率",
        "desc": "周期内 PR 的合并操作者与 PR 提交者不是同一人的比例"
      },
      "metric_011": {
        "title": "PR 评论频率",
        "desc": "平均每个 PR 下的对话/评论数量"
      },
      "metric_012": {
        "title": "分级代码审查时长",
        "desc": "按代码变更行数（XS/S/M/L/XL）分组统计的平均审查时间"
      }
    }
  },
  "model_003": {
    "title": "开发者基数",
    "desc": "开发者基数模型说明",
    "metrics": {
      "metric_013": {
        "title": "社区贡献者数量",
        "desc": "周期内有任何贡献行为的去重用户数"
      },
      "metric_014": {
        "title": "代码贡献者数量",
        "desc": "周期内有代码提交或 PR 合并或 PR 评论的去重用户数"
      },
      "metric_015": {
        "title": "非代码贡献者数量",
        "desc": "周期内仅参与讨论但未提交代码的用户数"
      }
    }
  },
  "model_004": {
    "title": "贡献活跃度",
    "desc": "贡献活跃度模型说明",
    "metrics": {
      "metric_016": {
        "title": "代码提交次数",
        "desc": "周期内新增的 Commit 总数"
      },
      "metric_017": {
        "title": "新增代码行数",
        "desc": "周期内代码行变动总量"
      },
      "metric_018": {
        "title": "PR 评论数量",
        "desc": "周期内产生的所有 Issue 和 PR 下的评论总和"
      },
      "metric_019": {
        "title": "Issue 建立数量",
        "desc": "周期内创建的 Issue 总数"
      },
      "metric_020": {
        "title": "Issue 评论数量",
        "desc": "周期内 Issue 下的评论总数"
      },
      "metric_021": {
        "title": "版本迭代次数",
        "desc": "周期内发布的 Release 数量"
      }
    }
  },
  "model_005": {
    "title": "社区流行度",
    "desc": "社区流行度模型说明",
    "metrics": {
      "metric_022": {
        "title": "Stars",
        "desc": "周期内新增的 Star 关注数"
      },
      "metric_023": {
        "title": "Forks",
        "desc": "周期内新增的 Fork 数"
      },
      "metric_024": {
        "title": "社交网站提及",
        "desc": "在 Twitter/X、Reddit、Hacker News 等社交媒体平台上的提及情况"
      },
      "metric_025": {
        "title": "Github 提及",
        "desc": "在 TOP50 万项目中，在 GitHub 上的 Issue、PR 和 README 文件中提及项目仓库"
      },
      "metric_026": {
        "title": "媒体报道",
        "desc": "指项目在在线新闻媒体、博客及科技媒体中被提及的次数"
      },
      "metric_027": {
        "title": "搜索查询量",
        "desc": "项目在搜索引擎中的查询量"
      }
    }
  },
  "model_006": {
    "title": "生态伙伴多样性",
    "desc": "生态伙伴多样性模型说明",
    "metrics": {
      "metric_028": {
        "title": "商业组织数量",
        "desc": "周期内通过贡献者邮箱域名或用户 Profile 识别出的去重商业公司数量"
      },
      "metric_029": {
        "title": "商业组织贡献者数量",
        "desc": "周期内隶属于商业组织（非个人邮箱）的活跃开发者数量"
      },
      "metric_030": {
        "title": "研究机构数量",
        "desc": "周期内参与贡献的研究机构组织个数"
      },
      "metric_031": {
        "title": "研究机构开发者数量",
        "desc": "周期内参与代码贡献的研究机构组织贡献者个数"
      },
      "metric_032": {
        "title": "个人主力贡献者数量",
        "desc": "周期内个人贡献代码超过个人总贡献代码的 50% 的为个人核心贡献者，低于 50% 的为常客贡献者"
      }
    }
  },
  "model_007": {
    "title": "生态伙伴影响力",
    "desc": "生态伙伴影响力模型说明",
    "metrics": {
      "metric_033": {
        "title": "商业组织生态影响力",
        "desc": "参与贡献的商业组织在生态的影响力"
      },
      "metric_034": {
        "title": "研究机构生态影响力",
        "desc": "参与贡献的研究机构在生态的影响力"
      },
      "metric_035": {
        "title": "个人贡献者生态影响力",
        "desc": "参与贡献的个人贡献者在生态的影响力"
      }
    }
  },
  "model_008": {
    "title": "技术采纳度",
    "desc": "技术采纳度模型说明",
    "metrics": {
      "metric_036": {
        "title": "软件包下载量",
        "desc": "开源软件下载的数量"
      },
      "metric_037": {
        "title": "开源软件采用量",
        "desc": "被其他开源项目（TOP 50w）引用的数量"
      },
      "metric_038": {
        "title": "商业软件采用量",
        "desc": "基于本项目的主流商业产品/服务数量"
      },
      "metric_039": {
        "title": "论文引用量",
        "desc": "论文引用量"
      }
    }
  },
  "model_009": {
    "title": "组织开放治理",
    "desc": "组织开放治理模型说明",
    "metrics": {
      "metric_040": {
        "title": "组织数",
        "desc": "周期内参与贡献的组织个数"
      },
      "metric_041": {
        "title": "组织代码贡献者",
        "desc": "周期内参与代码贡献的组织贡献者个数"
      },
      "metric_042": {
        "title": "组织代码贡献者占比",
        "desc": "周期内参与代码贡献的组织贡献者占总代码贡献者的比例"
      },
      "metric_043": {
        "title": "组织代码贡献量",
        "desc": "周期内组织贡献的代码行数"
      },
      "metric_044": {
        "title": "组织代码贡献量占比",
        "desc": "周期内组织贡献的代码占总代码量的比值"
      },
      "metric_045": {
        "title": "组织非代码贡献者",
        "desc": "周期内参与非代码贡献的组织贡献者个数"
      },
      "metric_046": {
        "title": "组织非代码贡献者占比",
        "desc": "周期内组织非代码贡献者占总非代码贡献者数量比例"
      },
      "metric_047": {
        "title": "组织非代码贡献量",
        "desc": "周期内组织非代码贡献量"
      },
      "metric_048": {
        "title": "组织非代码贡献量占比",
        "desc": "周期内组织非代码贡献量占总非代码贡献量比例"
      },
      "metric_049": {
        "title": "参与治理的组织数",
        "desc": "周期内在社区治理角色中，来自非社区发起组织的去重组织数量"
      },
      "metric_050": {
        "title": "组织管理者数量",
        "desc": "周期内在社区治理角色中，来自非社区发起组织的去重管理者数量"
      },
      "metric_051": {
        "title": "组织管理者数量占比",
        "desc": "周期内在社区治理角色中，来自组织（非个人）的管理者数量占总管理者数量的比例"
      }
    }
  },
  "model_010": {
    "title": "个人开放治理",
    "desc": "个人开放治理模型说明",
    "metrics": {
      "metric_052": {
        "title": "个人代码贡献者",
        "desc": "周期内有代码贡献行为（如代码提交、PR）的个人（非组织机构）贡献者数量"
      },
      "metric_053": {
        "title": "个人代码贡献者占比",
        "desc": "周期内个人代码贡献者数量占总代码贡献者数量的比例"
      },
      "metric_054": {
        "title": "个人代码贡献量",
        "desc": "周期内个人贡献者提交的代码行数"
      },
      "metric_055": {
        "title": "个人代码贡献量占比",
        "desc": "周期内个人贡献的代码行数占总代码贡献行数的比例"
      },
      "metric_056": {
        "title": "个人非代码贡献者",
        "desc": "周期内仅参与非代码贡献行为（如 Issue/PR 评论、文档）的个人（非组织机构）贡献者数量"
      },
      "metric_057": {
        "title": "个人非代码贡献者占比",
        "desc": "周期内个人非代码贡献者数量占总非代码贡献者数量的比例"
      },
      "metric_058": {
        "title": "个人非代码贡献量",
        "desc": "周期内个人贡献者提交的非代码贡献总次数（如 Issue/PR 评论数）"
      },
      "metric_059": {
        "title": "个人非代码贡献量占比",
        "desc": "周期内个人非代码贡献量占非代码总贡献量的比例"
      },
      "metric_060": {
        "title": "个人管理者数量",
        "desc": "周期内在社区治理角色中，来自个人的去重管理者数量"
      },
      "metric_061": {
        "title": "个人管理者数量占比",
        "desc": "周期内在社区治理角色中，来自个人的管理者数量占总管理者数量的比例"
      }
    }
  },
  "model_011": {
    "title": "开发者画像",
    "desc": "基于公开元数据和贡献行为，刻画开发者的背景、技能与参与意愿画像",
    "metrics": {}
  },
  "model_012": {
    "title": "开发者吸引",
    "desc": "衡量社区在当前周期吸引新增组织与新增个人开发者的能力",
    "metrics": {
      "metric_065": {
        "title": "新增组织数",
        "desc": "本周期内首次在社区产生有效贡献（代码或 Issue）的去重组织数量"
      },
      "metric_066": {
        "title": "新增组织代码开发者",
        "desc": "本周期内首次产生代码贡献的组织成员数量"
      },
      "metric_067": {
        "title": "新增组织非代码开发者",
        "desc": "本周期内首次产生非代码贡献的组织成员数量"
      },
      "metric_068": {
        "title": "新增个人代码开发者",
        "desc": "本周期内首次产生代码贡献的个人开发者数量"
      },
      "metric_069": {
        "title": "新增个人非代码开发者",
        "desc": "本周期内首次产生非代码贡献的个人开发者数量"
      }
    }
  },
  "model_013": {
    "title": "开发者参与度分层",
    "desc": "按组织/个人及代码/Issue 维度，将开发者划分为核心、常客与访客层级",
    "metrics": {
      "metric_070": {
        "title": "组织代码核心开发者及管理者数量",
        "desc": "本周期内代码贡献占比超过 50% 的组织贡献者数量"
      },
      "metric_071": {
        "title": "组织 Issue 核心开发者及管理者数量",
        "desc": "本周期内 Issue 活跃度排名靠前（前 50%）的组织成员数量"
      },
      "metric_072": {
        "title": "组织代码常客开发者数量",
        "desc": "本周期内有持续代码贡献但未达到核心标准的组织成员数量（代码贡献占比 20%-50%）"
      },
      "metric_073": {
        "title": "组织 Issue 常客开发者数量",
        "desc": "本周期内有持续 Issue 互动但未达到核心标准的组织成员数量"
      },
      "metric_074": {
        "title": "组织代码访客开发者数量",
        "desc": "本周期内仅有偶然或单次代码贡献的组织成员数量（代码贡献占比小于 20%）"
      },
      "metric_075": {
        "title": "组织 Issue 访客开发者数量",
        "desc": "本周期内仅有偶然 Issue 互动的组织成员数量"
      },
      "metric_076": {
        "title": "个人代码核心开发者及管理者数量",
        "desc": "本周期内代码贡献度排名靠前（前 50%）的个人开发者数量"
      },
      "metric_077": {
        "title": "个人 Issue 核心开发者及管理者数量",
        "desc": "本周期内 Issue 活跃度排名靠前（前 50%）的个人开发者数量"
      },
      "metric_078": {
        "title": "个人代码常客开发者数量",
        "desc": "本周期内代码贡献处于中间层级的个人开发者数量"
      },
      "metric_079": {
        "title": "个人 Issue 常客开发者数量",
        "desc": "本周期内 Issue 贡献量处于中间层级（20%-50%）的个人开发者数量"
      },
      "metric_080": {
        "title": "个人代码访客开发者数量",
        "desc": "本周期内代码贡献为低频或单次（小于 20%）的个人开发者数量"
      },
      "metric_081": {
        "title": "个人 Issue 访客开发者数量",
        "desc": "本周期内 Issue 贡献量为低频或单次（小于 20%）的个人开发者数量"
      }
    }
  },
  "model_014": {
    "title": "开发者晋升",
    "desc": "衡量开发者从常客或访客成长为核心开发者的数量",
    "metrics": {
      "metric_082": {
        "title": "组织代码核心开发者及管理者晋升数量",
        "desc": "上周期为非核心（常客或访客）、本周期成长为代码核心的组织成员数量"
      },
      "metric_083": {
        "title": "组织 Issue 核心开发者及管理者晋升数量",
        "desc": "上周期为非核心、本周期成长为 Issue 核心的组织成员数量"
      },
      "metric_084": {
        "title": "个人代码核心开发者及管理者晋升数量",
        "desc": "上周期为非核心、本周期成长为代码核心的个人开发者数量"
      },
      "metric_085": {
        "title": "个人 Issue 核心开发者及管理者晋升数量",
        "desc": "上周期为非核心、本周期成长为 Issue 核心的个人开发者数量"
      }
    }
  },
  "model_015": {
    "title": "核心开发者留存率",
    "desc": "衡量上周期核心开发者在本周期继续保持核心身份的比例",
    "metrics": {
      "metric_086": {
        "title": "组织代码核心开发者及管理者留存率",
        "desc": "上个周期的组织代码核心开发者，在本周期依然保持为代码核心开发者的比例"
      },
      "metric_087": {
        "title": "组织 Issue 核心开发者及管理者留存率",
        "desc": "上个周期的组织 Issue 核心开发者，在本周期依然保持为 Issue 核心开发者的比例"
      },
      "metric_088": {
        "title": "个人代码核心开发者及管理者留存率",
        "desc": "上个周期的个人代码核心开发者，在本周期依然保持为代码核心开发者的比例"
      },
      "metric_089": {
        "title": "个人 Issue 核心开发者及管理者留存率",
        "desc": "上个周期的个人 Issue 核心开发者，在本周期依然保持为 Issue 核心开发者的比例"
      }
    }
  },
  "model_016": {
    "title": "核心开发者淡出率",
    "desc": "衡量上周期核心开发者在本周期降级为常客或访客的比例",
    "metrics": {
      "metric_090": {
        "title": "组织代码核心开发者及管理者淡出率",
        "desc": "上个周期的组织代码核心开发者，在本周期降级为常客或访客的比例"
      },
      "metric_091": {
        "title": "组织 Issue 核心开发者及管理者淡出率",
        "desc": "上个周期的组织 Issue 核心开发者，在本周期降级为常客或访客的比例"
      },
      "metric_092": {
        "title": "个人代码核心开发者及管理者淡出率",
        "desc": "上个周期的个人代码核心开发者，在本周期降级为常客或访客的比例"
      },
      "metric_093": {
        "title": "个人 Issue 核心开发者及管理者淡出率",
        "desc": "上个周期的个人 Issue 核心开发者，在本周期降级为常客或访客的比例"
      }
    }
  },
  "model_017": {
    "title": "核心开发者流失率",
    "desc": "衡量上周期核心开发者在本周期没有任何贡献行为的比例",
    "metrics": {
      "metric_094": {
        "title": "组织代码核心开发者及管理者流失率",
        "desc": "上个周期的组织代码核心开发者，在本周期没有任何贡献行为的比例"
      },
      "metric_095": {
        "title": "组织 Issue 核心开发者及管理者流失率",
        "desc": "上个周期的组织 Issue 核心开发者，在本周期没有任何互动行为的比例"
      },
      "metric_096": {
        "title": "个人代码核心开发者及管理者流失率",
        "desc": "上个周期的个人代码核心开发者，在本周期没有任何贡献行为的比例"
      },
      "metric_097": {
        "title": "个人 Issue 核心开发者及管理者流失率",
        "desc": "上个周期的个人 Issue 核心开发者，在本周期没有任何互动行为的比例"
      }
    }
  },
  "model_018": {
    "title": "合法合规",
    "desc": "合法合规模型",
    "metrics": {
      "metric_098": {
        "title": "许可头与版权声明",
        "desc": "检查项目的所有源代码文件头部是否包含符合规范的 License Header 和 Copyright 文本"
      },
      "metric_099": {
        "title": "许可证包含",
        "desc": "检查仓库根目录下是否存在 LICENSE 文件，且内容为 OSI 认可的开源协议"
      },
      "metric_100": {
        "title": "许可证兼容性",
        "desc": "检测项目引入的第三方依赖库许可证是否与本项目声明的主许可证存在法律冲突"
      },
      "metric_101": {
        "title": "许可证与版权声明防篡改",
        "desc": "检查引入的代码片段是否完整保留了原上游软件的 License 及 Copyright 信息"
      }
    }
  },
  "model_019": {
    "title": "安全管理",
    "desc": "安全管理模型",
    "metrics": {
      "metric_102": {
        "title": "漏洞响应与披露",
        "desc": "评估项目是否建立了公开的漏洞反馈渠道及修复响应机制"
      },
      "metric_103": {
        "title": "安全漏洞",
        "desc": "扫描项目代码及依赖库中是否存在公开且未修复的 CVE 安全漏洞"
      }
    }
  },
  "model_020": {
    "title": "开发文档质量",
    "desc": "开发文档质量模型",
    "metrics": {
      "metric_104": {
        "title": "README",
        "desc": "检查仓库是否包含 README 文档，且清晰描述了项目功能"
      },
      "metric_105": {
        "title": "构建文档",
        "desc": "检查是否提供指导用户从源码编译/安装项目的文档说明"
      },
      "metric_106": {
        "title": "接口文档",
        "desc": "检查是否提供清晰的 API 接口定义文档或规范文件"
      },
      "metric_107": {
        "title": "Committers文件",
        "desc": "检查是否在仓库中公开维护了具备决策权的核心贡献者名单"
      }
    }
  },
  "model_021": {
    "title": "代码审查质量",
    "desc": "代码审查质量模型",
    "metrics": {
      "metric_108": {
        "title": "依赖可获得",
        "desc": "验证项目依赖的所有第三方库是否均可公开访问和下载"
      },
      "metric_109": {
        "title": "代码评审机制",
        "desc": "统计主分支合入的代码中，经过 Pull Request 同行评审（Review）的比例"
      },
      "metric_110": {
        "title": "片段引用",
        "desc": "识别引用的外部代码片段，并验证其来源声明的合规性"
      },
      "metric_111": {
        "title": "DCO",
        "desc": "检查所有代码提交（Commit）是否包含开发者原创性声明（Signed-off-by）"
      },
      "metric_112": {
        "title": "片段引用",
        "desc": "识别引用的外部代码片段，并验证其来源声明的合规性"
      },
      "metric_113": {
        "title": "专利风险",
        "desc": "分析引入的软件是否存在已知的专利侵权风险（基于OIN列表）"
      },
      "metric_114": {
        "title": "测试覆盖度",
        "desc": "衡量自动化测试用例执行时覆盖的代码行数占总代码行数的比例"
      }
    }
  },
  "model_022": {
    "title": "可信构建",
    "desc": "可信构建模型",
    "metrics": {
      "metric_115": {
        "title": "可构建",
        "desc": "验证项目能否使用公开工具从源码成功构建出可工作的系统"
      },
      "metric_116": {
        "title": "CI集成",
        "desc": "检查项目是否配置并启用了自动化的持续集成流水线"
      },
      "metric_117": {
        "title": "构建元数据可获取",
        "desc": "检查是否保存并提供了构建过程的输入元数据（环境、版本等）"
      },
      "metric_118": {
        "title": "一致性构建",
        "desc": "验证在相同环境下，同一源码是否能产出 Hash 值完全一致的二进制包"
      }
    }
  },
  "model_023": {
    "title": "发布质量",
    "desc": "发布质量模型",
    "metrics": {
      "metric_119": {
        "title": "SBOM检查",
        "desc": "验证发布的软件版本中是否包含标准的软件物料清单（SPDX/CycloneDX格式）"
      },
      "metric_120": {
        "title": "二进制制品包含",
        "desc": "检查源码仓库中是否违规包含了编译后的二进制文件"
      },
      "metric_121": {
        "title": "软件包签名",
        "desc": "验证发布的软件包是否经过数字签名以确保完整性和防篡改"
      },
      "metric_122": {
        "title": "Release Notes",
        "desc": "检查版本发布时是否提供了清晰的变更说明文档"
      }
    }
  },
  "model_024": {
    "title": "维护管理",
    "desc": "维护管理模型",
    "metrics": {
      "metric_123": {
        "title": "生命周期申明",
        "desc": "检查是否明确声明了软件版本的维护周期及停止支持（EOL）策略"
      },
      "metric_124": {
        "title": "安全漏洞修复时间",
        "desc": "统计从漏洞被报告到修复代码合入的平均耗时"
      }
    }
  },
  "model_999": {
    "title": "其他指标",
    "desc": "其他指标模型说明",
    "metrics": {
      "metric_062": {
        "title": "贡献者统计",
        "desc": "展示贡献者详情，包括贡献者数量、Top 贡献者、贡献组织数量、Top 贡献组织，以及每个贡献者的角色画像、里程画像、领域画像、组织归属和贡献量"
      },
      "metric_063": {
        "title": "Issue 管理",
        "desc": "展示 Issue 管理详情，包括新建 Issue 数量、Issue 解决率、未响应 Issue 数量、平均评论数，以及每个 Issue 的状态、处理时长、评论数等信息"
      },
      "metric_064": {
        "title": "PR 管理",
        "desc": "展示 PR 管理详情，包括新建 PR 数量、PR 解决率、未响应 PR 数量、代码提交数量，以及每个 PR 的状态、处理时长、审核者等信息"
      }
    }
  }
}